sqlabeat/__init__.py
sqlabeat-0.1.dist-info/DESCRIPTION.rst
sqlabeat-0.1.dist-info/METADATA
sqlabeat-0.1.dist-info/RECORD
sqlabeat-0.1.dist-info/WHEEL
sqlabeat-0.1.dist-info/metadata.json
sqlabeat-0.1.dist-info/top_level.txt
