Metadata-Version: 2.0
Name: sqlabeat
Version: 0.1
Summary: SQLAlchemy Celery Beat Scheduler
Home-page: https://github.com/kashifpk/celerybeat-sqlalchemy
Author: Kashif Iftikhar
Author-email: kashif@compulife.com.pk
License: GPLv2
Keywords: Celery Beat SQLAlchemy Scheduler
Platform: UNKNOWN
Classifier: Development Status :: 4 - Beta
Classifier: Programming Language :: Python :: 2
Classifier: Programming Language :: Python :: 2.6
Classifier: Programming Language :: Python :: 2.7
Classifier: Programming Language :: Python :: 3
Classifier: Programming Language :: Python :: 3.2
Classifier: Programming Language :: Python :: 3.3
Classifier: Programming Language :: Python :: 3.4
Classifier: Programming Language :: Python :: 3.5
Requires-Dist: sqlalchemy
